brotlipy-0.7.0.dist-info/METADATA
brotlipy-0.7.0.dist-info/LICENSE
brotlipy-0.7.0.dist-info/RECORD
brotlipy-0.7.0.dist-info/WHEEL
brotlipy-0.7.0.dist-info/top_level.txt
brotli/brotli.py
brotli/_brotli.abi3.so
brotli/__init__.py
brotli/build.py
