Metadata-Version: 2.0
Name: brotlipy
Version: 0.7.0
Summary: Python binding to the Brotli library
Home-page: https://github.com/python-hyper/brotlipy/
Author: Cory Benfield
Author-email: cory@lukasa.co.uk
License: MIT
Platform: UNKNOWN
Classifier: Programming Language :: Python :: Implementation :: CPython
Classifier: Programming Language :: Python :: Implementation :: PyPy
Classifier: Programming Language :: Python :: 2
Classifier: Programming Language :: Python :: 2.7
Classifier: Programming Language :: Python :: 3
Classifier: Programming Language :: Python :: 3.3
Classifier: Programming Language :: Python :: 3.4
Classifier: Programming Language :: Python :: 3.5
Classifier: Programming Language :: Python :: 3.6
Requires-Dist: cffi (>=1.0.0)
Requires-Dist: enum34 (>=1.0.4,<2); python_version == "2.7" or python_version == "3.3"
